skelform_pygame/__init__.py
skelform_pygame-0.2.2.1.dist-info/METADATA
skelform_pygame-0.2.2.1.dist-info/WHEEL
skelform_pygame-0.2.2.1.dist-info/RECORD
