Metadata-Version: 2.4
Name: skelform_pygame
Version: 0.2.2.1
Summary: SkelForm runtime for Pygame. Uses the generic runtime
Author-email: Retropaint <darkglasses1122@gmail.com>
License-Expression: MIT
Classifier: Operating System :: OS Independent
Classifier: Programming Language :: Python :: 3
Requires-Python: >=3.9
Requires-Dist: dacite>=1.9.2
Requires-Dist: pygame>=2.6.1
Requires-Dist: skelform-python>=0.2.0.1
